sexy_ai/__init__.py
sexy_ai-0.1.dist-info/METADATA
sexy_ai-0.1.dist-info/WHEEL
sexy_ai-0.1.dist-info/top_level.txt
sexy_ai-0.1.dist-info/RECORD
